behavior/__init__.py
behavior/component_set.py
behavior/component_set_version.py
behavior/container.py
behavior/container_version.py
behavior/experience.py
behavior/experience_collection.py
cli/__init__.py
cli/cli.py
commands/__init__.py
commands/api.py
commands/app_builder.py
commands/app_builder_version.py
commands/asset.py
commands/asset_version.py
commands/component_set.py
commands/component_set_version.py
commands/container.py
commands/container_version.py
commands/env.py
commands/experience.py
commands/experience_collection.py
commands/microservice.py
commands/microservice_version.py
commands/organization.py
commands/profile.py
commands/widget.py
commands/widget_version.py
pyke/__init__.py
pyke/auth.py
pyke/container_util.py
pyke/exceptions.py
pyke/helptxt.py
pyke/luma.py
pyke/menu.py
pyke/tarsum.py
pyke/util.py
luma-12.dist-info/LICENSE
luma-12.dist-info/METADATA
luma-12.dist-info/WHEEL
luma-12.dist-info/entry_points.txt
luma-12.dist-info/top_level.txt
luma-12.dist-info/RECORD
