Metadata-Version: 2.1
Name: luma
Version: 12
Summary: A CLI to interact with the Lumavate platform
Author-email: Lumavate <development@lumavate.com>
License: Copyright (c) <> Lumavate
Classifier: Programming Language :: Python :: 3.8
Requires-Python: >=3.8
License-File: LICENSE
Requires-Dist: click>=8.0
Requires-Dist: pycparser==2.21
Requires-Dist: pyparsing==3.0.9
Requires-Dist: python-dateutil==2.8
Requires-Dist: requests>=2.28.1
Requires-Dist: docker>=6.0.0
